apihelpers4py/__init__.py
apihelpers4py/_version.py
apihelpers4py/io.py
apihelpers4py-0.2.dist-info/METADATA
apihelpers4py-0.2.dist-info/WHEEL
apihelpers4py-0.2.dist-info/top_level.txt
apihelpers4py-0.2.dist-info/RECORD
