Metadata-Version: 2.1
Name: apihelpers4py
Version: 0.2
Summary: Helpers for API development
Home-page: https://gitlab.com/Pierre_VF/apihelpers4py
Author: PVF
Author-email: pvf@dtime.ai
License: UNKNOWN
Platform: UNKNOWN
Classifier: Programming Language :: Python :: 3
Classifier: License :: OSI Approved :: MIT License
Classifier: Operating System :: OS Independent
Requires-Python: >=3.7
Requires-Dist: pandas
Requires-Dist: requests
Requires-Dist: dateutils
Provides-Extra: dash
Requires-Dist: dash ; extra == 'dash'
Requires-Dist: plotly ; extra == 'dash'
Provides-Extra: dev
Requires-Dist: black ; extra == 'dev'
Requires-Dist: pytest ; extra == 'dev'
Requires-Dist: versioneer ; extra == 'dev'
Requires-Dist: coverage ; extra == 'dev'
Requires-Dist: build ; extra == 'dev'
Requires-Dist: pre-commit ; extra == 'dev'
Requires-Dist: fastapi[all] ; extra == 'dev'
Provides-Extra: fastapi
Requires-Dist: fastapi[all] ; extra == 'fastapi'
